{"ast":[null,{"children":[0,2,11],"kind":"file","start":[0,0]},{"children":[3,5,7,9],"end":[1,0],"kind":"imports","start":[1,0]},{"children":[4],"end":[1,0],"kind":"import","start":[1,0]},{"end":[1,7],"kind":"module","start":[1,7],"value":["vectors","tuple"]},{"children":[6],"end":[2,0],"kind":"import","start":[2,0]},{"end":[2,7],"kind":"module","start":[2,7],"value":["data","real","basic"]},{"children":[8],"end":[3,0],"kind":"import","start":[3,0]},{"end":[3,7],"kind":"module","start":[3,7],"value":["vectors","tuple","tactics"]},{"children":[10],"end":[4,0],"kind":"import","start":[4,0]},{"end":[4,7],"kind":"module","start":[4,7],"value":["game","vector_spaces_world","one_smul"]},{"children":[12,14,106],"end":[4,7],"kind":"commands","start":[4,7]},{"children":[13],"end":[5,15],"kind":"namespace","start":[5,0]},{"end":[5,10],"kind":"ident","start":[5,10],"value":"tuple"},{"children":[0,0,0,15,0,48,105,0],"end":[35,3],"kind":"theorem","start":[24,0]},{"end":[24,6],"kind":"ident","start":[24,6],"value":"scalar_dist_2"},null,{"children":[19,23,28],"end":[24,24],"kind":"binders","start":[24,24]},{"children":[20],"end":[24,25],"kind":"vars","start":[24,25]},{"children":[18,0,21],"end":[24,25],"kind":"binder_4","start":[24,25]},{"end":[24,25],"kind":"ident","start":[24,25],"value":"n"},{"end":[24,30],"kind":"notation","pexpr":1,"start":[24,29],"value":"exprℕ"},{"children":[24,25],"end":[24,33],"kind":"vars","start":[24,33]},{"children":[22,0,26],"end":[24,33],"kind":"binder_0","start":[24,33]},{"end":[24,33],"kind":"ident","start":[24,33],"value":"a"},{"end":[24,35],"kind":"ident","start":[24,35],"value":"b"},{"end":[24,40],"kind":"notation","pexpr":2,"start":[24,39],"value":"exprℝ"},{"children":[29],"end":[24,43],"kind":"vars","start":[24,43]},{"children":[27,0,32],"end":[24,43],"kind":"binder_0","start":[24,43]},{"end":[24,43],"kind":"ident","start":[24,43],"value":"v"},{"end":[24,48],"kind":"notation","pexpr":3,"start":[24,47],"value":"exprℝ"},{"end":[24,52],"kind":"ident","pexpr":4,"start":[24,51],"value":"n"},{"children":[30,31],"end":[24,52],"kind":"notation","pexpr":7,"start":[24,49],"value":"expr ^ "},{"end":[24,57],"kind":"ident","pexpr":8,"start":[24,56],"value":"a"},{"end":[24,61],"kind":"ident","pexpr":9,"start":[24,60],"value":"b"},{"children":[33,34],"end":[24,61],"kind":"notation","pexpr":12,"start":[24,58],"value":"expr + "},{"children":[35],"end":[24,62],"kind":"(","pexpr":12,"start":[24,55]},{"children":[36],"end":[24,62],"kind":"notation","pexpr":12,"start":[24,55],"value":"("},{"end":[24,66],"kind":"ident","pexpr":13,"start":[24,65],"value":"v"},{"children":[37,38],"end":[24,66],"kind":"notation","pexpr":16,"start":[24,63],"value":"expr • "},{"end":[24,70],"kind":"ident","pexpr":17,"start":[24,69],"value":"a"},{"end":[24,74],"kind":"ident","pexpr":18,"start":[24,73],"value":"v"},{"children":[40,41],"end":[24,74],"kind":"notation","pexpr":21,"start":[24,71],"value":"expr • "},{"end":[24,78],"kind":"ident","pexpr":22,"start":[24,77],"value":"b"},{"end":[24,82],"kind":"ident","pexpr":23,"start":[24,81],"value":"v"},{"children":[43,44],"end":[24,82],"kind":"notation","pexpr":26,"start":[24,79],"value":"expr • "},{"children":[42,45],"end":[24,82],"kind":"notation","pexpr":29,"start":[24,75],"value":"expr + "},{"children":[39,46],"end":[24,82],"kind":"notation","pexpr":32,"start":[24,67],"value":"expr = "},{"children":[17,47],"end":[24,82],"kind":"notation","pexpr":57,"start":[24,22],"value":"Pi"},{"children":[0,0,50,52,62,75],"end":[35,3],"kind":"begin","pexpr":833,"start":[25,0]},{"children":[51],"end":[26,8],"kind":"tactic","pexpr":102,"start":[26,2],"value":"intros"},{"end":[26,8],"kind":"parse","pexpr":99,"start":[26,8]},{"children":[53,56,57,61],"end":[27,23],"kind":"tactic","pexpr":180,"start":[27,2],"value":"induction"},{"children":[55],"end":[27,13],"kind":"parse","pexpr":150,"start":[27,12]},{"end":[27,13],"kind":"ident","pexpr":147,"start":[27,12],"value":"n"},{"children":[54],"end":[27,14],"kind":"expr","start":[27,12]},{"end":[27,13],"kind":"parse","pexpr":153,"start":[27,14]},{"children":[58,59,60],"end":[27,23],"kind":"parse","pexpr":171,"start":[27,14]},{"end":[27,14],"kind":"token","start":[27,14],"value":"with"},{"end":[27,19],"kind":"ident","start":[27,19],"value":"n"},{"end":[27,21],"kind":"ident","start":[27,21],"value":"hn"},{"end":[27,23],"kind":"parse","pexpr":177,"start":[27,23]},{"children":[0,0,63,68],"end":[29,11],"kind":"{","pexpr":360,"start":[28,2]},{"children":[64,67],"end":[28,11],"kind":"tactic","pexpr":268,"start":[28,4],"value":"cases"},{"children":[66],"end":[28,11],"kind":"parse","pexpr":262,"start":[28,10]},{"end":[28,11],"kind":"ident","pexpr":259,"start":[28,10],"value":"v"},{"children":[65],"end":[28,11],"kind":"expr","start":[28,10]},{"end":[28,11],"kind":"parse","pexpr":265,"start":[28,11]},{"children":[69,70,71,72,73,74],"end":[29,8],"kind":"tactic","pexpr":334,"start":[29,4],"value":"simp"},{"end":[29,8],"kind":"parse","pexpr":306,"start":[29,8]},{"end":[29,8],"kind":"parse","pexpr":309,"start":[29,8]},{"end":[29,8],"kind":"parse","pexpr":312,"start":[29,8]},{"end":[29,8],"kind":"parse","pexpr":316,"start":[29,8]},{"end":[29,8],"kind":"parse","pexpr":319,"start":[29,8]},{"end":[29,8],"kind":"parse","pexpr":331,"start":[29,8]},{"children":[0,0,76,85,92,93,98],"end":[34,23],"kind":"{","pexpr":809,"start":[30,2]},{"children":[77,80],"end":[30,24],"kind":"tactic","pexpr":466,"start":[30,4],"value":"cases"},{"children":[79],"end":[30,11],"kind":"parse","pexpr":442,"start":[30,10]},{"end":[30,11],"kind":"ident","pexpr":439,"start":[30,10],"value":"v"},{"children":[78],"end":[30,12],"kind":"expr","start":[30,10]},{"children":[81,82,83,84],"end":[30,24],"kind":"parse","pexpr":463,"start":[30,12]},{"end":[30,12],"kind":"token","start":[30,12],"value":"with"},{"end":[30,17],"kind":"ident","start":[30,17],"value":"n"},{"end":[30,19],"kind":"ident","start":[30,19],"value":"v₁"},{"end":[30,22],"kind":"ident","start":[30,22],"value":"vₙ"},{"children":[86,87,88,89,90,91],"end":[31,8],"kind":"tactic","pexpr":525,"start":[31,4],"value":"simp"},{"end":[31,8],"kind":"parse","pexpr":503,"start":[31,8]},{"end":[31,8],"kind":"parse","pexpr":506,"start":[31,8]},{"end":[31,8],"kind":"parse","pexpr":508,"start":[31,8]},{"end":[31,8],"kind":"parse","pexpr":511,"start":[31,8]},{"end":[31,8],"kind":"parse","pexpr":514,"start":[31,8]},{"end":[31,8],"kind":"parse","pexpr":522,"start":[31,8]},{"end":[32,9],"kind":"tactic","pexpr":564,"start":[32,4],"value":"split"},{"children":[0,0,94],"end":[33,17],"kind":"{","pexpr":674,"start":[33,4]},{"children":[95,96,97],"end":[33,14],"kind":"tactic","pexpr":649,"start":[33,6],"value":"linarith"},{"end":[33,14],"kind":"parse","pexpr":637,"start":[33,14]},{"end":[33,14],"kind":"parse","pexpr":640,"start":[33,14]},{"end":[33,14],"kind":"parse","pexpr":646,"start":[33,14]},{"children":[0,0,99],"end":[34,20],"kind":"{","pexpr":782,"start":[34,4]},{"children":[100],"end":[34,17],"kind":"tactic","pexpr":757,"start":[34,6],"value":"exact"},{"children":[104],"end":[34,17],"kind":"parse","pexpr":754,"start":[34,12]},{"end":[34,14],"kind":"ident","pexpr":749,"start":[34,12],"value":"hn"},{"end":[34,17],"kind":"ident","pexpr":751,"start":[34,15],"value":"vₙ"},{"children":[101,102],"end":[34,17],"kind":"app","pexpr":752,"start":[34,12]},{"children":[103],"end":[34,17],"kind":"expr","start":[34,12]},{"children":[49],"end":[35,3],"kind":"notation","pexpr":834,"start":[25,0],"value":"begin"},{"children":[107],"end":[37,9],"kind":"end","start":[37,0]},{"end":[37,4],"kind":"ident","start":[37,4],"value":"tuple"}],"comments":[{"end":[1,28],"start":[1,23],"text":" hide"},{"end":[1,28],"start":[1,23],"text":" hide"},{"end":[2,29],"start":[2,25],"text":"hide"},{"end":[2,29],"start":[2,25],"text":"hide"},{"end":[3,35],"start":[3,31],"text":"hide"},{"end":[3,35],"start":[3,31],"text":"hide"},{"end":[4,47],"start":[4,43],"text":"hide"},{"end":[4,47],"start":[4,43],"text":"hide"},{"end":[5,23],"start":[5,18],"text":" hide"},{"end":[17,0],"start":[8,2],"text":" \n\n# Vector Spaces World\n\nStrategy:\nThis level will give you more practice with induction!\n\n## Level 6: `Distributive property 2` \n\n"},{"end":[22,0],"start":[19,2],"text":" Lemma\n(a + b) • v = a • v + b • v\n\n"},{"end":[37,17],"start":[37,12],"text":" hide"}],"expr":[null,{"const":["nat",[]]},{"const":["real",[]]},{"const":["real",[]]},{"local":{"bi":4,"name":"n","pp":"n","type":1}},{"const":[["has_pow","pow"],[]]},{"app":[5,3]},{"app":[6,4]},{"local":{"bi":0,"name":"a","pp":"a","type":2}},{"local":{"bi":0,"name":"b","pp":"b","type":2}},{"const":[["has_add","add"],[]]},{"app":[10,8]},{"app":[11,9]},{"local":{"bi":0,"name":"v","pp":"v","type":7}},{"const":[["has_smul","smul"],[]]},{"app":[14,12]},{"app":[15,13]},{"local":{"bi":0,"name":"a","pp":"a","type":2}},{"local":{"bi":0,"name":"v","pp":"v","type":7}},{"const":[["has_smul","smul"],[]]},{"app":[19,17]},{"app":[20,18]},{"local":{"bi":0,"name":"b","pp":"b","type":2}},{"local":{"bi":0,"name":"v","pp":"v","type":7}},{"const":[["has_smul","smul"],[]]},{"app":[24,22]},{"app":[25,23]},{"const":[["has_add","add"],[]]},{"app":[27,21]},{"app":[28,26]},{"const":["eq",[]]},{"app":[30,16]},{"app":[31,29]},{"var":2},{"app":[6,33]},{"var":2},{"app":[10,35]},{"var":1},{"app":[36,37]},{"app":[14,38]},{"var":0},{"app":[39,40]},{"app":[30,41]},{"var":2},{"app":[19,43]},{"var":0},{"app":[44,45]},{"app":[27,46]},{"var":1},{"app":[24,48]},{"var":0},{"app":[49,50]},{"app":[47,51]},{"app":[42,52]},{"Pi":{"bi":0,"body":53,"dom":34,"name":"v"}},{"Pi":{"bi":0,"body":54,"dom":2,"name":"b"}},{"Pi":{"bi":0,"body":55,"dom":2,"name":"a"}},{"Pi":{"bi":4,"body":56,"dom":1,"name":"n"}},{"const":[["interactive","executor","execute_explicit"],[]]},{"const":["tactic",[]]},{"app":[58,59]},{"const":[["has_bind","seq"],[]]},{"const":[["has_bind","seq"],[]]},{"const":[["has_bind","seq"],[]]},{"const":[["has_bind","seq"],[]]},{"const":[["tactic","save_info"],[]]},{"const":[[4,"_",545],[]]},{"prenum":{"args":[],"value":"25"}},{"app":[66,67]},{"prenum":{"args":[],"value":"0"}},{"app":[68,69]},{"annotation":{"args":[70],"name":"anonymous_constructor"}},{"app":[65,71]},{"app":[64,72]},{"const":[["has_bind","seq"],[]]},{"const":[["tactic","save_info"],[]]},{"const":[[4,"_",546],[]]},{"prenum":{"args":[],"value":"26"}},{"app":[76,77]},{"prenum":{"args":[],"value":"2"}},{"app":[78,79]},{"annotation":{"args":[80],"name":"anonymous_constructor"}},{"app":[75,81]},{"app":[74,82]},{"const":[["tactic","istep"],[]]},{"prenum":{"args":[],"value":"26"}},{"app":[84,85]},{"prenum":{"args":[],"value":"2"}},{"app":[86,87]},{"prenum":{"args":[],"value":"26"}},{"app":[88,89]},{"prenum":{"args":[],"value":"2"}},{"app":[90,91]},{"prenum":{"args":[],"value":"50"}},{"app":[92,93]},{"const":[["tactic","interactive","intros"],[]]},{"const":[["list","nil"],[0]]},{"const":["name",[]]},{"app":[96,97]},{"annotation":{"args":[98],"name":"as_is"}},{"app":[95,99]},{"app":[94,100]},{"app":[83,101]},{"app":[73,102]},{"app":[63,103]},{"const":[["has_bind","seq"],[]]},{"const":[["tactic","save_info"],[]]},{"const":[[4,"_",547],[]]},{"prenum":{"args":[],"value":"27"}},{"app":[107,108]},{"prenum":{"args":[],"value":"3"}},{"app":[109,110]},{"annotation":{"args":[111],"name":"anonymous_constructor"}},{"app":[106,112]},{"app":[105,113]},{"const":[["has_bind","seq"],[]]},{"const":[["tactic","save_info"],[]]},{"const":[[4,"_",549],[]]},{"prenum":{"args":[],"value":"27"}},{"app":[117,118]},{"prenum":{"args":[],"value":"2"}},{"app":[119,120]},{"annotation":{"args":[121],"name":"anonymous_constructor"}},{"app":[116,122]},{"app":[115,123]},{"const":[["tactic","istep"],[]]},{"prenum":{"args":[],"value":"27"}},{"app":[125,126]},{"prenum":{"args":[],"value":"2"}},{"app":[127,128]},{"prenum":{"args":[],"value":"27"}},{"app":[129,130]},{"prenum":{"args":[],"value":"2"}},{"app":[131,132]},{"prenum":{"args":[],"value":"52"}},{"app":[133,134]},{"const":[["tactic","interactive","induction"],[]]},{"const":[["prod","mk"],[0,0]]},{"const":["option",[0]]},{"app":[138,97]},{"app":[137,139]},{"const":["pexpr",[]]},{"app":[140,141]},{"const":[["option","none"],[0]]},{"app":[143,97]},{"app":[142,144]},{"const":[[4,"_",548],[]]},{"local":{"bi":0,"name":"n","pp":"n","type":146}},{"expr_quote_macro":{"args":[],"reflected":false,"value":147}},{"app":[145,148]},{"annotation":{"args":[149],"name":"as_is"}},{"app":[136,150]},{"app":[143,97]},{"annotation":{"args":[152],"name":"as_is"}},{"app":[151,153]},{"const":[["list","cons"],[0]]},{"app":[155,97]},{"const":[["name","mk_string"],[]]},{"string_macro":{"args":[],"value":"n"}},{"app":[157,158]},{"const":[["name","anonymous"],[]]},{"app":[159,160]},{"app":[156,161]},{"app":[155,97]},{"string_macro":{"args":[],"value":"hn"}},{"app":[157,164]},{"app":[165,160]},{"app":[163,166]},{"app":[96,97]},{"app":[167,168]},{"app":[162,169]},{"annotation":{"args":[170],"name":"as_is"}},{"app":[154,171]},{"const":[["option","none"],[0]]},{"const":["list",[0]]},{"app":[174,97]},{"app":[173,175]},{"annotation":{"args":[176],"name":"as_is"}},{"app":[172,177]},{"app":[135,178]},{"app":[124,179]},{"app":[114,180]},{"app":[104,181]},{"app":[62,182]},{"const":[["has_bind","seq"],[]]},{"const":[["has_bind","seq"],[]]},{"const":[["tactic","save_info"],[]]},{"const":[[4,"_",550],[]]},{"prenum":{"args":[],"value":"28"}},{"app":[187,188]},{"prenum":{"args":[],"value":"3"}},{"app":[189,190]},{"annotation":{"args":[191],"name":"anonymous_constructor"}},{"app":[186,192]},{"app":[185,193]},{"const":[["has_bind","seq"],[]]},{"const":[["tactic","save_info"],[]]},{"const":[[4,"_",558],[]]},{"prenum":{"args":[],"value":"28"}},{"app":[197,198]},{"prenum":{"args":[],"value":"2"}},{"app":[199,200]},{"annotation":{"args":[201],"name":"anonymous_constructor"}},{"app":[196,202]},{"app":[195,203]},{"const":[["tactic","istep"],[]]},{"prenum":{"args":[],"value":"28"}},{"app":[205,206]},{"prenum":{"args":[],"value":"2"}},{"app":[207,208]},{"prenum":{"args":[],"value":"29"}},{"app":[209,210]},{"prenum":{"args":[],"value":"10"}},{"app":[211,212]},{"prenum":{"args":[],"value":"62"}},{"app":[213,214]},{"const":[["tactic","solve1"],[]]},{"const":[["interactive","executor","execute_explicit"],[]]},{"const":["tactic",[]]},{"app":[217,218]},{"const":[["has_bind","seq"],[]]},{"const":[["has_bind","seq"],[]]},{"const":[["has_bind","seq"],[]]},{"const":[["tactic","save_info"],[]]},{"const":[[4,"_",551],[]]},{"prenum":{"args":[],"value":"28"}},{"app":[224,225]},{"prenum":{"args":[],"value":"2"}},{"app":[226,227]},{"annotation":{"args":[228],"name":"anonymous_constructor"}},{"app":[223,229]},{"app":[222,230]},{"const":[["has_bind","seq"],[]]},{"const":[["tactic","save_info"],[]]},{"const":[[4,"_",553],[]]},{"prenum":{"args":[],"value":"28"}},{"app":[234,235]},{"prenum":{"args":[],"value":"4"}},{"app":[236,237]},{"annotation":{"args":[238],"name":"anonymous_constructor"}},{"app":[233,239]},{"app":[232,240]},{"const":[["tactic","istep"],[]]},{"prenum":{"args":[],"value":"28"}},{"app":[242,243]},{"prenum":{"args":[],"value":"4"}},{"app":[244,245]},{"prenum":{"args":[],"value":"28"}},{"app":[246,247]},{"prenum":{"args":[],"value":"4"}},{"app":[248,249]},{"prenum":{"args":[],"value":"63"}},{"app":[250,251]},{"const":[["tactic","interactive","cases"],[]]},{"app":[137,139]},{"app":[254,141]},{"app":[143,97]},{"app":[255,256]},{"const":[[4,"_",552],[]]},{"local":{"bi":0,"name":"v","pp":"v","type":258}},{"expr_quote_macro":{"args":[],"reflected":false,"value":259}},{"app":[257,260]},{"annotation":{"args":[261],"name":"as_is"}},{"app":[253,262]},{"app":[96,97]},{"annotation":{"args":[264],"name":"as_is"}},{"app":[263,265]},{"app":[252,266]},{"app":[241,267]},{"app":[231,268]},{"app":[221,269]},{"const":[["has_bind","seq"],[]]},{"const":[["tactic","save_info"],[]]},{"const":[[4,"_",554],[]]},{"prenum":{"args":[],"value":"29"}},{"app":[273,274]},{"prenum":{"args":[],"value":"5"}},{"app":[275,276]},{"annotation":{"args":[277],"name":"anonymous_constructor"}},{"app":[272,278]},{"app":[271,279]},{"const":[["has_bind","seq"],[]]},{"const":[["has_bind","seq"],[]]},{"const":[["tactic","save_info"],[]]},{"const":[[4,"_",555],[]]},{"prenum":{"args":[],"value":"29"}},{"app":[284,285]},{"prenum":{"args":[],"value":"4"}},{"app":[286,287]},{"annotation":{"args":[288],"name":"anonymous_constructor"}},{"app":[283,289]},{"app":[282,290]},{"const":[["tactic","istep"],[]]},{"prenum":{"args":[],"value":"29"}},{"app":[292,293]},{"prenum":{"args":[],"value":"4"}},{"app":[294,295]},{"prenum":{"args":[],"value":"29"}},{"app":[296,297]},{"prenum":{"args":[],"value":"4"}},{"app":[298,299]},{"prenum":{"args":[],"value":"68"}},{"app":[300,301]},{"const":[["tactic","interactive","simp"],[]]},{"const":["unit",[]]},{"app":[173,304]},{"annotation":{"args":[305],"name":"as_is"}},{"app":[303,306]},{"app":[173,304]},{"annotation":{"args":[308],"name":"as_is"}},{"app":[307,309]},{"const":[["bool","ff"],[]]},{"annotation":{"args":[311],"name":"as_is"}},{"app":[310,312]},{"const":[["tactic","simp_arg_type"],[]]},{"app":[96,314]},{"annotation":{"args":[315],"name":"as_is"}},{"app":[313,316]},{"app":[96,97]},{"annotation":{"args":[318],"name":"as_is"}},{"app":[317,319]},{"const":[["interactive","loc","ns"],[]]},{"const":["option",[0]]},{"const":["name",[]]},{"app":[322,323]},{"app":[155,324]},{"app":[143,323]},{"app":[325,326]},{"app":[96,324]},{"app":[327,328]},{"app":[321,329]},{"annotation":{"args":[330],"name":"as_is"}},{"app":[320,331]},{"app":[302,332]},{"app":[291,333]},{"app":[281,334]},{"const":[["tactic","save_info"],[]]},{"const":[[4,"_",556],[]]},{"prenum":{"args":[],"value":"29"}},{"app":[337,338]},{"prenum":{"args":[],"value":"11"}},{"app":[339,340]},{"annotation":{"args":[341],"name":"anonymous_constructor"}},{"app":[336,342]},{"app":[335,343]},{"app":[280,344]},{"app":[270,345]},{"app":[220,346]},{"const":[["tactic","save_info"],[]]},{"const":[[4,"_",557],[]]},{"prenum":{"args":[],"value":"29"}},{"app":[349,350]},{"prenum":{"args":[],"value":"10"}},{"app":[351,352]},{"annotation":{"args":[353],"name":"anonymous_constructor"}},{"app":[348,354]},{"app":[347,355]},{"app":[219,356]},{"app":[216,357]},{"app":[215,358]},{"app":[204,359]},{"app":[194,360]},{"app":[184,361]},{"const":[["has_bind","seq"],[]]},{"const":[["tactic","save_info"],[]]},{"const":[[4,"_",559],[]]},{"prenum":{"args":[],"value":"30"}},{"app":[365,366]},{"prenum":{"args":[],"value":"3"}},{"app":[367,368]},{"annotation":{"args":[369],"name":"anonymous_constructor"}},{"app":[364,370]},{"app":[363,371]},{"const":[["has_bind","seq"],[]]},{"const":[["has_bind","seq"],[]]},{"const":[["tactic","save_info"],[]]},{"const":[[4,"_",583],[]]},{"prenum":{"args":[],"value":"30"}},{"app":[376,377]},{"prenum":{"args":[],"value":"2"}},{"app":[378,379]},{"annotation":{"args":[380],"name":"anonymous_constructor"}},{"app":[375,381]},{"app":[374,382]},{"const":[["tactic","istep"],[]]},{"prenum":{"args":[],"value":"30"}},{"app":[384,385]},{"prenum":{"args":[],"value":"2"}},{"app":[386,387]},{"prenum":{"args":[],"value":"34"}},{"app":[388,389]},{"prenum":{"args":[],"value":"22"}},{"app":[390,391]},{"prenum":{"args":[],"value":"75"}},{"app":[392,393]},{"const":[["tactic","solve1"],[]]},{"const":[["interactive","executor","execute_explicit"],[]]},{"const":["tactic",[]]},{"app":[396,397]},{"const":[["has_bind","seq"],[]]},{"const":[["has_bind","seq"],[]]},{"const":[["has_bind","seq"],[]]},{"const":[["has_bind","seq"],[]]},{"const":[["tactic","save_info"],[]]},{"const":[[4,"_",560],[]]},{"prenum":{"args":[],"value":"30"}},{"app":[404,405]},{"prenum":{"args":[],"value":"2"}},{"app":[406,407]},{"annotation":{"args":[408],"name":"anonymous_constructor"}},{"app":[403,409]},{"app":[402,410]},{"const":[["has_bind","seq"],[]]},{"const":[["tactic","save_info"],[]]},{"const":[[4,"_",562],[]]},{"prenum":{"args":[],"value":"30"}},{"app":[414,415]},{"prenum":{"args":[],"value":"4"}},{"app":[416,417]},{"annotation":{"args":[418],"name":"anonymous_constructor"}},{"app":[413,419]},{"app":[412,420]},{"const":[["tactic","istep"],[]]},{"prenum":{"args":[],"value":"30"}},{"app":[422,423]},{"prenum":{"args":[],"value":"4"}},{"app":[424,425]},{"prenum":{"args":[],"value":"30"}},{"app":[426,427]},{"prenum":{"args":[],"value":"4"}},{"app":[428,429]},{"prenum":{"args":[],"value":"76"}},{"app":[430,431]},{"const":[["tactic","interactive","cases"],[]]},{"app":[137,139]},{"app":[434,141]},{"app":[143,97]},{"app":[435,436]},{"const":[[4,"_",561],[]]},{"local":{"bi":0,"name":"v","pp":"v","type":438}},{"expr_quote_macro":{"args":[],"reflected":false,"value":439}},{"app":[437,440]},{"annotation":{"args":[441],"name":"as_is"}},{"app":[433,442]},{"app":[155,97]},{"string_macro":{"args":[],"value":"n"}},{"app":[157,445]},{"app":[446,160]},{"app":[444,447]},{"app":[155,97]},{"string_macro":{"args":[],"value":"v₁"}},{"app":[157,450]},{"app":[451,160]},{"app":[449,452]},{"app":[155,97]},{"string_macro":{"args":[],"value":"vₙ"}},{"app":[157,455]},{"app":[456,160]},{"app":[454,457]},{"app":[96,97]},{"app":[458,459]},{"app":[453,460]},{"app":[448,461]},{"annotation":{"args":[462],"name":"as_is"}},{"app":[443,463]},{"app":[432,464]},{"app":[421,465]},{"app":[411,466]},{"app":[401,467]},{"const":[["has_bind","seq"],[]]},{"const":[["tactic","save_info"],[]]},{"const":[[4,"_",563],[]]},{"prenum":{"args":[],"value":"31"}},{"app":[471,472]},{"prenum":{"args":[],"value":"5"}},{"app":[473,474]},{"annotation":{"args":[475],"name":"anonymous_constructor"}},{"app":[470,476]},{"app":[469,477]},{"const":[["has_bind","seq"],[]]},{"const":[["has_bind","seq"],[]]},{"const":[["tactic","save_info"],[]]},{"const":[[4,"_",564],[]]},{"prenum":{"args":[],"value":"31"}},{"app":[482,483]},{"prenum":{"args":[],"value":"4"}},{"app":[484,485]},{"annotation":{"args":[486],"name":"anonymous_constructor"}},{"app":[481,487]},{"app":[480,488]},{"const":[["tactic","istep"],[]]},{"prenum":{"args":[],"value":"31"}},{"app":[490,491]},{"prenum":{"args":[],"value":"4"}},{"app":[492,493]},{"prenum":{"args":[],"value":"31"}},{"app":[494,495]},{"prenum":{"args":[],"value":"4"}},{"app":[496,497]},{"prenum":{"args":[],"value":"85"}},{"app":[498,499]},{"const":[["tactic","interactive","simp"],[]]},{"app":[173,304]},{"annotation":{"args":[502],"name":"as_is"}},{"app":[501,503]},{"app":[173,304]},{"annotation":{"args":[505],"name":"as_is"}},{"app":[504,506]},{"annotation":{"args":[311],"name":"as_is"}},{"app":[507,508]},{"app":[96,314]},{"annotation":{"args":[510],"name":"as_is"}},{"app":[509,511]},{"app":[96,97]},{"annotation":{"args":[513],"name":"as_is"}},{"app":[512,514]},{"app":[155,324]},{"app":[143,323]},{"app":[516,517]},{"app":[96,324]},{"app":[518,519]},{"app":[321,520]},{"annotation":{"args":[521],"name":"as_is"}},{"app":[515,522]},{"app":[500,523]},{"app":[489,524]},{"app":[479,525]},{"const":[["tactic","save_info"],[]]},{"const":[[4,"_",565],[]]},{"prenum":{"args":[],"value":"32"}},{"app":[528,529]},{"prenum":{"args":[],"value":"5"}},{"app":[530,531]},{"annotation":{"args":[532],"name":"anonymous_constructor"}},{"app":[527,533]},{"app":[526,534]},{"app":[478,535]},{"app":[468,536]},{"app":[400,537]},{"const":[["has_bind","seq"],[]]},{"const":[["has_bind","seq"],[]]},{"const":[["has_bind","seq"],[]]},{"const":[["tactic","save_info"],[]]},{"const":[[4,"_",566],[]]},{"prenum":{"args":[],"value":"32"}},{"app":[543,544]},{"prenum":{"args":[],"value":"4"}},{"app":[545,546]},{"annotation":{"args":[547],"name":"anonymous_constructor"}},{"app":[542,548]},{"app":[541,549]},{"const":[["tactic","istep"],[]]},{"prenum":{"args":[],"value":"32"}},{"app":[551,552]},{"prenum":{"args":[],"value":"4"}},{"app":[553,554]},{"prenum":{"args":[],"value":"32"}},{"app":[555,556]},{"prenum":{"args":[],"value":"4"}},{"app":[557,558]},{"prenum":{"args":[],"value":"92"}},{"app":[559,560]},{"const":[["tactic","interactive","split"],[]]},{"app":[561,562]},{"app":[550,563]},{"app":[540,564]},{"const":[["has_bind","seq"],[]]},{"const":[["tactic","save_info"],[]]},{"const":[[4,"_",567],[]]},{"prenum":{"args":[],"value":"33"}},{"app":[568,569]},{"prenum":{"args":[],"value":"5"}},{"app":[570,571]},{"annotation":{"args":[572],"name":"anonymous_constructor"}},{"app":[567,573]},{"app":[566,574]},{"const":[["has_bind","seq"],[]]},{"const":[["tactic","save_info"],[]]},{"const":[[4,"_",572],[]]},{"prenum":{"args":[],"value":"33"}},{"app":[578,579]},{"prenum":{"args":[],"value":"4"}},{"app":[580,581]},{"annotation":{"args":[582],"name":"anonymous_constructor"}},{"app":[577,583]},{"app":[576,584]},{"const":[["tactic","istep"],[]]},{"prenum":{"args":[],"value":"33"}},{"app":[586,587]},{"prenum":{"args":[],"value":"4"}},{"app":[588,589]},{"prenum":{"args":[],"value":"33"}},{"app":[590,591]},{"prenum":{"args":[],"value":"16"}},{"app":[592,593]},{"prenum":{"args":[],"value":"93"}},{"app":[594,595]},{"const":[["tactic","solve1"],[]]},{"const":[["interactive","executor","execute_explicit"],[]]},{"const":["tactic",[]]},{"app":[598,599]},{"const":[["has_bind","seq"],[]]},{"const":[["has_bind","seq"],[]]},{"const":[["tactic","save_info"],[]]},{"const":[[4,"_",568],[]]},{"prenum":{"args":[],"value":"33"}},{"app":[604,605]},{"prenum":{"args":[],"value":"4"}},{"app":[606,607]},{"annotation":{"args":[608],"name":"anonymous_constructor"}},{"app":[603,609]},{"app":[602,610]},{"const":[["has_bind","seq"],[]]},{"const":[["has_bind","seq"],[]]},{"const":[["tactic","save_info"],[]]},{"const":[[4,"_",569],[]]},{"prenum":{"args":[],"value":"33"}},{"app":[615,616]},{"prenum":{"args":[],"value":"6"}},{"app":[617,618]},{"annotation":{"args":[619],"name":"anonymous_constructor"}},{"app":[614,620]},{"app":[613,621]},{"const":[["tactic","istep"],[]]},{"prenum":{"args":[],"value":"33"}},{"app":[623,624]},{"prenum":{"args":[],"value":"6"}},{"app":[625,626]},{"prenum":{"args":[],"value":"33"}},{"app":[627,628]},{"prenum":{"args":[],"value":"6"}},{"app":[629,630]},{"prenum":{"args":[],"value":"94"}},{"app":[631,632]},{"const":[["tactic","interactive","linarith"],[]]},{"const":["unit",[]]},{"app":[173,635]},{"annotation":{"args":[636],"name":"as_is"}},{"app":[634,637]},{"app":[173,635]},{"annotation":{"args":[639],"name":"as_is"}},{"app":[638,640]},{"const":["list",[0]]},{"const":["pexpr",[]]},{"app":[642,643]},{"app":[173,644]},{"annotation":{"args":[645],"name":"as_is"}},{"app":[641,646]},{"app":[633,647]},{"app":[622,648]},{"app":[612,649]},{"const":[["tactic","save_info"],[]]},{"const":[[4,"_",570],[]]},{"prenum":{"args":[],"value":"33"}},{"app":[652,653]},{"prenum":{"args":[],"value":"17"}},{"app":[654,655]},{"annotation":{"args":[656],"name":"anonymous_constructor"}},{"app":[651,657]},{"app":[650,658]},{"app":[611,659]},{"app":[601,660]},{"const":[["tactic","save_info"],[]]},{"const":[[4,"_",571],[]]},{"prenum":{"args":[],"value":"33"}},{"app":[663,664]},{"prenum":{"args":[],"value":"16"}},{"app":[665,666]},{"annotation":{"args":[667],"name":"anonymous_constructor"}},{"app":[662,668]},{"app":[661,669]},{"app":[600,670]},{"app":[597,671]},{"app":[596,672]},{"app":[585,673]},{"app":[575,674]},{"app":[565,675]},{"app":[539,676]},{"const":[["has_bind","seq"],[]]},{"const":[["tactic","save_info"],[]]},{"const":[[4,"_",573],[]]},{"prenum":{"args":[],"value":"34"}},{"app":[680,681]},{"prenum":{"args":[],"value":"5"}},{"app":[682,683]},{"annotation":{"args":[684],"name":"anonymous_constructor"}},{"app":[679,685]},{"app":[678,686]},{"const":[["has_bind","seq"],[]]},{"const":[["has_bind","seq"],[]]},{"const":[["tactic","save_info"],[]]},{"const":[[4,"_",580],[]]},{"prenum":{"args":[],"value":"34"}},{"app":[691,692]},{"prenum":{"args":[],"value":"4"}},{"app":[693,694]},{"annotation":{"args":[695],"name":"anonymous_constructor"}},{"app":[690,696]},{"app":[689,697]},{"const":[["tactic","istep"],[]]},{"prenum":{"args":[],"value":"34"}},{"app":[699,700]},{"prenum":{"args":[],"value":"4"}},{"app":[701,702]},{"prenum":{"args":[],"value":"34"}},{"app":[703,704]},{"prenum":{"args":[],"value":"19"}},{"app":[705,706]},{"prenum":{"args":[],"value":"98"}},{"app":[707,708]},{"const":[["tactic","solve1"],[]]},{"const":[["interactive","executor","execute_explicit"],[]]},{"const":["tactic",[]]},{"app":[711,712]},{"const":[["has_bind","seq"],[]]},{"const":[["has_bind","seq"],[]]},{"const":[["tactic","save_info"],[]]},{"const":[[4,"_",574],[]]},{"prenum":{"args":[],"value":"34"}},{"app":[717,718]},{"prenum":{"args":[],"value":"4"}},{"app":[719,720]},{"annotation":{"args":[721],"name":"anonymous_constructor"}},{"app":[716,722]},{"app":[715,723]},{"const":[["has_bind","seq"],[]]},{"const":[["has_bind","seq"],[]]},{"const":[["tactic","save_info"],[]]},{"const":[[4,"_",577],[]]},{"prenum":{"args":[],"value":"34"}},{"app":[728,729]},{"prenum":{"args":[],"value":"6"}},{"app":[730,731]},{"annotation":{"args":[732],"name":"anonymous_constructor"}},{"app":[727,733]},{"app":[726,734]},{"const":[["tactic","istep"],[]]},{"prenum":{"args":[],"value":"34"}},{"app":[736,737]},{"prenum":{"args":[],"value":"6"}},{"app":[738,739]},{"prenum":{"args":[],"value":"34"}},{"app":[740,741]},{"prenum":{"args":[],"value":"6"}},{"app":[742,743]},{"prenum":{"args":[],"value":"99"}},{"app":[744,745]},{"const":[["tactic","interactive","exact"],[]]},{"const":[[4,"_",575],[]]},{"local":{"bi":0,"name":"hn","pp":"hn","type":748}},{"const":[[4,"_",576],[]]},{"local":{"bi":0,"name":"vₙ","pp":"vₙ","type":750}},{"app":[749,751]},{"expr_quote_macro":{"args":[],"reflected":false,"value":752}},{"annotation":{"args":[753],"name":"as_is"}},{"app":[747,754]},{"app":[746,755]},{"app":[735,756]},{"app":[725,757]},{"const":[["tactic","save_info"],[]]},{"const":[[4,"_",578],[]]},{"prenum":{"args":[],"value":"34"}},{"app":[760,761]},{"prenum":{"args":[],"value":"20"}},{"app":[762,763]},{"annotation":{"args":[764],"name":"anonymous_constructor"}},{"app":[759,765]},{"app":[758,766]},{"app":[724,767]},{"app":[714,768]},{"const":[["tactic","save_info"],[]]},{"const":[[4,"_",579],[]]},{"prenum":{"args":[],"value":"34"}},{"app":[771,772]},{"prenum":{"args":[],"value":"19"}},{"app":[773,774]},{"annotation":{"args":[775],"name":"anonymous_constructor"}},{"app":[770,776]},{"app":[769,777]},{"app":[713,778]},{"app":[710,779]},{"app":[709,780]},{"app":[698,781]},{"app":[688,782]},{"const":[["tactic","save_info"],[]]},{"const":[[4,"_",581],[]]},{"prenum":{"args":[],"value":"34"}},{"app":[785,786]},{"prenum":{"args":[],"value":"23"}},{"app":[787,788]},{"annotation":{"args":[789],"name":"anonymous_constructor"}},{"app":[784,790]},{"app":[783,791]},{"app":[687,792]},{"app":[677,793]},{"app":[538,794]},{"app":[399,795]},{"const":[["tactic","save_info"],[]]},{"const":[[4,"_",582],[]]},{"prenum":{"args":[],"value":"34"}},{"app":[798,799]},{"prenum":{"args":[],"value":"22"}},{"app":[800,801]},{"annotation":{"args":[802],"name":"anonymous_constructor"}},{"app":[797,803]},{"app":[796,804]},{"app":[398,805]},{"app":[395,806]},{"app":[394,807]},{"app":[383,808]},{"app":[373,809]},{"const":[["tactic","save_info"],[]]},{"const":[[4,"_",584],[]]},{"prenum":{"args":[],"value":"35"}},{"app":[812,813]},{"prenum":{"args":[],"value":"1"}},{"app":[814,815]},{"annotation":{"args":[816],"name":"anonymous_constructor"}},{"app":[811,817]},{"app":[810,818]},{"app":[372,819]},{"app":[362,820]},{"app":[183,821]},{"app":[61,822]},{"const":[["tactic","save_info"],[]]},{"const":[[4,"_",585],[]]},{"prenum":{"args":[],"value":"35"}},{"app":[825,826]},{"prenum":{"args":[],"value":"0"}},{"app":[827,828]},{"annotation":{"args":[829],"name":"anonymous_constructor"}},{"app":[824,830]},{"app":[823,831]},{"app":[60,832]},{"annotation":{"args":[833],"name":"by"}}],"file":1,"level":["0"]}